argumentative/__about__.py
argumentative/__init__.py
argumentative-0.0.1.dist-info/METADATA
argumentative-0.0.1.dist-info/WHEEL
argumentative-0.0.1.dist-info/licenses/LICENSE.md
argumentative-0.0.1.dist-info/RECORD
