Metadata-Version: 2.3
Name: argumentative
Version: 0.0.1
Summary: opinionated, simple arg parsing
Project-URL: Documentation, https://github.com/allura-org/argumentative#readme
Project-URL: Issues, https://github.com/allura-org/argumentative/issues
Project-URL: Source, https://github.com/allura-org/argumentative
Author-email: fizz~ <fizzarolli@riseup.net>
License: LicenseRef-Hippocratic-3.0-BDS-CL-Eco-Extr-Law-Mil-SV
Classifier: Development Status :: 4 - Beta
Classifier: Programming Language :: Python
Classifier: Programming Language :: Python :: 3.10
Classifier: Programming Language :: Python :: 3.11
Classifier: Programming Language :: Python :: 3.12
Classifier: Programming Language :: Python :: Implementation :: CPython
Classifier: Programming Language :: Python :: Implementation :: PyPy
Requires-Python: >=3.10
Requires-Dist: libcst
Requires-Dist: msgspec
